setup.py
cumtbscore/__init__.py
cumtbscore/utils.py
cumtbscore.egg-info/PKG-INFO
cumtbscore.egg-info/SOURCES.txt
cumtbscore.egg-info/dependency_links.txt
cumtbscore.egg-info/requires.txt
cumtbscore.egg-info/top_level.txt