Metadata-Version: 1.0
Name: cumtbscore
Version: 0.4.0
Summary: Student score interface for CUMTB
Home-page: https://github.com/x1ah/Daily_scripts/tree/restructure/StuScore
Author: x1ah
Author-email: x1ahgxq@gmail.com
License: MIT
Keywords: cumtb score spider python cli
Platform: UNKNOWN
